cfn_dep2layer-0.1.5.data/scripts/dep2layer
dep2layer/__init__.py
dep2layer/downloaders.py
dep2layer/main.py
dep2layer/nodejs/run.sh
dep2layer/python/run.sh
cfn_dep2layer-0.1.5.dist-info/METADATA
cfn_dep2layer-0.1.5.dist-info/WHEEL
cfn_dep2layer-0.1.5.dist-info/top_level.txt
cfn_dep2layer-0.1.5.dist-info/RECORD
